{"_id":{"$oid":"654eefa60c88d354f96b897b"},"piso":1,"letra":"A","extension":1000,"numero_habitaciones":2,"alquilado":true,"nombre_propietario":"Sebastián Cortés","mail_contacto":"sebasttes@gmail.com","createdAt":{"$date":"2023-11-11T03:06:14.067Z"},"updatedAt":{"$date":"2023-11-11T03:06:14.067Z"}}
{"_id":{"$oid":"654ef0b20c88d354f96b897f"},"piso":1,"letra":"B","extension":1000,"numero_habitaciones":2,"alquilado":false,"nombre_propietario":"Montserrat Soler","mail_contacto":"montseer@gmail.com","createdAt":{"$date":"2023-11-11T03:10:42.306Z"},"updatedAt":{"$date":"2023-11-11T03:35:27.561Z"}}
{"_id":{"$oid":"654ef18d0c88d354f96b8982"},"piso":2,"letra":"A","extension":2000,"numero_habitaciones":3,"alquilado":true,"nombre_propietario":"Lucia Cano","mail_contacto":"lucia.cano@gmail.com","createdAt":{"$date":"2023-11-11T03:14:21.85Z"},"updatedAt":{"$date":"2023-11-11T03:14:21.85Z"}}
{"_id":{"$oid":"654ef1d00c88d354f96b8985"},"piso":2,"letra":"B","extension":2000,"numero_habitaciones":3,"alquilado":true,"nombre_propietario":"Luisa Reyes","mail_contacto":"luisaryes@hotmail.com","createdAt":{"$date":"2023-11-11T03:15:28.288Z"},"updatedAt":{"$date":"2023-11-11T03:15:28.288Z"}}
{"_id":{"$oid":"654ef2220c88d354f96b8987"},"piso":2,"letra":"C","extension":2000,"numero_habitaciones":3,"alquilado":false,"nombre_propietario":"Pablo Hidalgo","mail_contacto":"pablogoku2003@mundor.com","createdAt":{"$date":"2023-11-11T03:16:50.402Z"},"updatedAt":{"$date":"2023-11-11T03:16:50.402Z"}}
{"_id":{"$oid":"654ef2740c88d354f96b898a"},"piso":9,"letra":"A","extension":6000,"numero_habitaciones":4,"alquilado":false,"nombre_propietario":"Felipe Ramos Jiménez","mail_contacto":"feliperamos@gmail.com","createdAt":{"$date":"2023-11-11T03:18:12.776Z"},"updatedAt":{"$date":"2023-11-11T20:06:34.109Z"}}
{"_id":{"$oid":"654fdf39ebb298b26a902f75"},"piso":13,"letra":"B","extension":12345,"numero_habitaciones":66,"alquilado":true,"nombre_propietario":"Luci Fernandez","mail_contacto":"lucifer666@gmail.com","createdAt":{"$date":"2023-11-11T20:08:25.759Z"},"updatedAt":{"$date":"2023-11-11T21:41:59.58Z"}}
{"_id":{"$oid":"654fea162cd814d5a408abc3"},"piso":13,"letra":"K","extension":10000,"numero_habitaciones":5,"alquilado":false,"nombre_propietario":"Luci Fernandez","mail_contacto":"lucifer666@gmail.com","createdAt":{"$date":"2023-11-11T20:54:46.681Z"},"updatedAt":{"$date":"2023-11-11T20:54:46.681Z"}}
